dorito/__init__.py
dorito/generative_agent.py
dorito/memory.py
dorito/utils.py
dorito-0.1.dist-info/LICENSE
dorito-0.1.dist-info/METADATA
dorito-0.1.dist-info/WHEEL
dorito-0.1.dist-info/top_level.txt
dorito-0.1.dist-info/RECORD
