Metadata-Version: 2.1
Name: dorito
Version: 0.1
License-File: LICENSE
Requires-Dist: openai
